musculoskeletal/models/__init__.py
musculoskeletal/models/atlas_meshes/femur_left_mean_rigid_LLP26.geof
musculoskeletal/models/atlas_meshes/femur_left_quartic_flat.ens
musculoskeletal/models/atlas_meshes/femur_left_quartic_flat.mesh
musculoskeletal/models/atlas_meshes/femur_right_mirrored_from_left_mean_rigid_LLP26.geof
musculoskeletal/models/atlas_meshes/femur_right_quartic_flat.ens
musculoskeletal/models/atlas_meshes/femur_right_quartic_flat.mesh
musculoskeletal/models/atlas_meshes/patella_11_left.ens
musculoskeletal/models/atlas_meshes/patella_11_left.mesh
musculoskeletal/models/atlas_meshes/patella_11_right.ens
musculoskeletal/models/atlas_meshes/patella_11_right.mesh
musculoskeletal/models/atlas_meshes/patella_left_mean_rigid_LLP26.geof
musculoskeletal/models/atlas_meshes/patella_right_mirrored_from_left_mean_rigid_LLP26.geof
musculoskeletal/models/atlas_meshes/pelvis_combined_cubic_flat.ens
musculoskeletal/models/atlas_meshes/pelvis_combined_cubic_flat.mesh
musculoskeletal/models/atlas_meshes/pelvis_combined_cubic_mean_rigid_LLP26.geof
musculoskeletal/models/atlas_meshes/tibia_fibula_cubic_left_mean_rigid_LLP26.geof
musculoskeletal/models/atlas_meshes/tibia_fibula_cubic_right_mirrored_from_left_mean_rigid_LLP26.geof
musculoskeletal/models/atlas_meshes/tibia_fibula_left_cubic_flat.ens
musculoskeletal/models/atlas_meshes/tibia_fibula_left_cubic_flat.mesh
musculoskeletal/models/atlas_meshes/tibia_fibula_right_cubic_flat.ens
musculoskeletal/models/atlas_meshes/tibia_fibula_right_cubic_flat.mesh
musculoskeletal/models/shape_models/LLP26_right_mirrored_from_left_rigid.pc
musculoskeletal/models/shape_models/LLP26_rigid.pc
musculoskeletal_models-0.2.4.dist-info/LICENSE
musculoskeletal_models-0.2.4.dist-info/METADATA
musculoskeletal_models-0.2.4.dist-info/WHEEL
musculoskeletal_models-0.2.4.dist-info/top_level.txt
musculoskeletal_models-0.2.4.dist-info/RECORD
