Metadata-Version: 2.1
Name: musculoskeletal-models
Version: 0.2.4
Summary: Collection of musculoskeletal principal component models, used by the GIAS3 Python package.
Author: Auckland Bioengineering Institute
License: Mozilla Public License 2.0 (MPL-2.0)
Project-URL: Homepage, https://github.com/musculoskeletal/models
License-File: LICENSE
